OSTutor/.gitignore
OSTutor/__init__.py
OSTutor/__main__.py
OSTutor/mytest.py
OSTutor/py_run_main.py
OSTutor/requirements.txt
OSTutor/test.ipynb
OSTutor/test.py
OSTutor/src/__init__.py
OSTutor/src/firstflag.txt
OSTutor/src/__pycache__/__init__.cpython-312.pyc
OSTutor/src/assets/data.zip
OSTutor/src/assets/csv/inst_data.csv
OSTutor/src/assets/csv/synonyms_data.csv
OSTutor/src/assets/db/.gitkeep
OSTutor/src/assets/db/ostutor 备份.db
OSTutor/src/assets/db/ostutor.db
OSTutor/src/assets/model/nltk_data/corpora/stopwords.zip
OSTutor/src/assets/model/nltk_data/corpora/wordnet.zip
OSTutor/src/assets/model/nltk_data/corpora/stopwords/README
OSTutor/src/assets/model/nltk_data/corpora/stopwords/arabic
OSTutor/src/assets/model/nltk_data/corpora/stopwords/azerbaijani
OSTutor/src/assets/model/nltk_data/corpora/stopwords/basque
OSTutor/src/assets/model/nltk_data/corpora/stopwords/bengali
OSTutor/src/assets/model/nltk_data/corpora/stopwords/catalan
OSTutor/src/assets/model/nltk_data/corpora/stopwords/chinese
OSTutor/src/assets/model/nltk_data/corpora/stopwords/danish
OSTutor/src/assets/model/nltk_data/corpora/stopwords/dutch
OSTutor/src/assets/model/nltk_data/corpora/stopwords/english
OSTutor/src/assets/model/nltk_data/corpora/stopwords/finnish
OSTutor/src/assets/model/nltk_data/corpora/stopwords/french
OSTutor/src/assets/model/nltk_data/corpora/stopwords/german
OSTutor/src/assets/model/nltk_data/corpora/stopwords/greek
OSTutor/src/assets/model/nltk_data/corpora/stopwords/hebrew
OSTutor/src/assets/model/nltk_data/corpora/stopwords/hinglish
OSTutor/src/assets/model/nltk_data/corpora/stopwords/hungarian
OSTutor/src/assets/model/nltk_data/corpora/stopwords/indonesian
OSTutor/src/assets/model/nltk_data/corpora/stopwords/italian
OSTutor/src/assets/model/nltk_data/corpora/stopwords/kazakh
OSTutor/src/assets/model/nltk_data/corpora/stopwords/nepali
OSTutor/src/assets/model/nltk_data/corpora/stopwords/norwegian
OSTutor/src/assets/model/nltk_data/corpora/stopwords/portuguese
ostutor-1.0.1.dist-info/LICENSE
ostutor-1.0.1.dist-info/METADATA
ostutor-1.0.1.dist-info/WHEEL
ostutor-1.0.1.dist-info/entry_points.txt
ostutor-1.0.1.dist-info/top_level.txt
ostutor-1.0.1.dist-info/RECORD
