Metadata-Version: 2.1
Name: ostutor
Version: 1.0.1
Summary: The goal of the App is to develop a new tool that, after receiving a few keywords given by the user, returns possibly relevant commands and other further relevant help information.
Home-page: https://gitlab.eduxiji.net/T202414655993206/project2210132-239674
Author: Zhenxin Liang,Zijian Chen,Qiyong Wu
Author-email: t202414655993206@eduxiji.net
License: Mulan PSL v1
License-File: LICENSE
Requires-Dist: click ==8.1.7
Requires-Dist: colorama ==0.4.6
Requires-Dist: nltk ==3.8.1
Requires-Dist: npyscreen ==4.10.5
Requires-Dist: pandas ==2.2.2
Requires-Dist: prompt-toolkit ==3.0.43
Requires-Dist: rich ==13.7.1
Requires-Dist: scikit-learn ==1.5.1
Requires-Dist: tqdm ==4.66.4
Requires-Dist: wcwidth ==0.2.13
